cronradar/__init__.py
cronradar-0.0.4.dist-info/licenses/LICENSE
cronradar-0.0.4.dist-info/METADATA
cronradar-0.0.4.dist-info/WHEEL
cronradar-0.0.4.dist-info/top_level.txt
cronradar-0.0.4.dist-info/RECORD
