Metadata-Version: 2.4
Name: cronradar
Version: 0.0.4
Summary: Dead-simple cron job monitoring with auto-registration. Two functions: ping() and sync_monitor(). Self-healing monitors.
Home-page: https://github.com/cronradar/cronradar-python
Author: Administrator
Author-email: contact@cronradar.com
License: Proprietary
Project-URL: Documentation, https://cronradar.com/docs
Project-URL: Source, https://github.com/cronradar/cronradar-python
Project-URL: Tracker, https://github.com/cronradar/cronradar-python/issues
Keywords: cron monitoring scheduler job task ping sync auto-register
Classifier: Development Status :: 5 - Production/Stable
Classifier: Intended Audience :: Developers
Classifier: License :: Other/Proprietary License
Classifier: Operating System :: OS Independent
Classifier: Programming Language :: Python :: 3
Classifier: Programming Language :: Python :: 3.8
Classifier: Programming Language :: Python :: 3.9
Classifier: Programming Language :: Python :: 3.10
Classifier: Programming Language :: Python :: 3.11
Classifier: Programming Language :: Python :: 3.12
Classifier: Topic :: Software Development :: Libraries :: Python Modules
Classifier: Topic :: System :: Monitoring
Requires-Python: >=3.8
License-File: LICENSE
Dynamic: author
Dynamic: author-email
Dynamic: classifier
Dynamic: description
Dynamic: description-content-type
Dynamic: home-page
Dynamic: keywords
Dynamic: license
Dynamic: license-file
Dynamic: project-url
Dynamic: requires-python
Dynamic: summary
